rosh/__init__.py
rosh/commands/__init__.py
rosh/commands/disable/__init__.py
rosh/commands/disable/interface/__init__.py
rosh/commands/enable/__init__.py
rosh/commands/enable/interface/__init__.py
rosh/commands/exit/__init__.py
rosh/commands/help/__init__.py
rosh/commands/identify/__init__.py
rosh/commands/identify/interface/__init__.py
rosh/commands/ifstatecli/__init__.py
rosh/commands/lbu/__init__.py
rosh/commands/monitor/__init__.py
rosh/commands/mtr/__init__.py
rosh/commands/netns/__init__.py
rosh/commands/ping/__init__.py
rosh/commands/renegotiate/__init__.py
rosh/commands/renegotiate/interface/__init__.py
rosh/commands/reset/__init__.py
rosh/commands/reset/interface/__init__.py
rosh/commands/shell/__init__.py
rosh/commands/show/__init__.py
rosh/commands/show/bridge/__init__.py
rosh/commands/show/bridge/fdb/__init__.py
rosh/commands/show/ifstate/__init__.py
rosh/commands/show/ifstate/config/__init__.py
rosh/commands/show/interface/__init__.py
rosh/commands/show/ip/__init__.py
rosh/commands/show/ip/address/__init__.py
rosh/commands/show/ip/neighbour/__init__.py
rosh/commands/show/ip/route/__init__.py
rosh/commands/show/ip/rule/__init__.py
rosh/commands/show/ipv6/__init__.py
rosh/commands/show/ipv6/address/__init__.py
rosh/commands/show/ipv6/neighbour/__init__.py
rosh/commands/show/ipv6/route/__init__.py
rosh/commands/show/ipv6/rule/__init__.py
rosh/commands/show/netns/__init__.py
rosh/commands/ssh/__init__.py
rosh/commands/tcpdump/__init__.py
rosh/commands/telnet/__init__.py
rosh/commands/traceroute/__init__.py
rosh/completer/__init__.py
rosh/filters/__init__.py
rosh/filters/exclude/__init__.py
rosh/filters/include/__init__.py
rosh/filters/tee/__init__.py
rosh/lookup/__init__.py
rosh/output/__init__.py
rosh/output/details.py
rosh/output/table.py
rosh/rtlookup/__init__.py
rosh/validator/__init__.py
rosh-0.1.8.dist-info/LICENSE
rosh-0.1.8.dist-info/METADATA
rosh-0.1.8.dist-info/WHEEL
rosh-0.1.8.dist-info/entry_points.txt
rosh-0.1.8.dist-info/top_level.txt
rosh-0.1.8.dist-info/RECORD
