Metadata-Version: 2.1
Name: rosh
Version: 0.1.8
Summary: router shell is a interactive diagnostic shell for Linux
Home-page: https://codeberg.org/liske/rosh
Author: Thomas Liske
Author-email: thomas@fiasko-nw.net
License: GPL3+
License-File: LICENSE
Requires-Dist: cachetools
Requires-Dist: prettytable
Requires-Dist: prompt-toolkit
Requires-Dist: pyroute2
Requires-Dist: fuzzyfinder
Requires-Dist: setproctitle
Provides-Extra: ifstate
Requires-Dist: ifstate ; extra == 'ifstate'
